p2d2/.deprecated/dashboard.js
p2d2/.deprecated/row_detail.js
p2d2/.deprecated/shared.js
p2d2/.deprecated/table_detail.js
p2d2/__init__.py
p2d2/database.py
p2d2/routers.py
p2d2/templates/admin.js
p2d2/templates/admin_dashboard.html
p2d2/templates/database.css
p2d2/templates/row_card.html
p2d2/templates/row_detail.html
p2d2/templates/table_card.html
p2d2/templates/table_detail.html
p2d2/templates/test.html
p2d2/test_p2d2.py
pd2d2-0.1.0.dist-info/LICENSE
pd2d2-0.1.0.dist-info/METADATA
pd2d2-0.1.0.dist-info/WHEEL
pd2d2-0.1.0.dist-info/RECORD
