Metadata-Version: 2.3
Name: pd2d2
Version: 0.1.0
Summary: Pickled Parquetted Dataframed Database
Author: Miles Copeland Luce
Requires-Python: >=3.13,<4.0
Classifier: Programming Language :: Python :: 3
Classifier: Programming Language :: Python :: 3.13
Requires-Dist: fastapi (>=0.116.1,<0.117.0)
Requires-Dist: fastj2 (>=0.1.11,<0.2.0)
Requires-Dist: jinja2 (>=3.1.6,<4.0.0)
Requires-Dist: loguru (>=0.7.3,<0.8.0)
Requires-Dist: pandas (>=2.3.1,<3.0.0)
Requires-Dist: starlette (>=0.47.2,<0.48.0)
Requires-Dist: toomanyconfigs (>=0.2.82,<0.3.0)
Requires-Dist: toomanysessions (>=0.1.9956,<0.2.0)
Requires-Dist: toomanythreads (>=0.2.4,<0.3.0)
